{
  "id": "plimsoll-security",
  "name": "Plimsoll Financial Guard",
  "kind": "context-engine",
  "description": "Deterministic financial security firewall for AI agents handling money. Five engines: loop detection, spend-rate limits, credential exfiltration defense, high-value confirmation gates, and amount anomaly detection. Zero-dependency, fail-closed.",
  "version": "2.2.0",
  "configSchema": {
    "type": "object",
    "additionalProperties": false,
    "properties": {
      "enabled": {
        "type": "boolean",
        "default": true
      },
      "maxVelocityCentsPerWindow": {
        "type": "number",
        "default": 50000,
        "description": "Maximum cumulative spend (in cents) within the velocity window"
      },
      "velocityWindowSeconds": {
        "type": "number",
        "default": 300,
        "description": "Sliding window duration in seconds for velocity enforcement"
      },
      "loopThreshold": {
        "type": "number",
        "default": 3,
        "description": "Number of identical tool calls before hard block"
      },
      "loopWindowSeconds": {
        "type": "number",
        "default": 60,
        "description": "Sliding window duration in seconds for loop detection"
      },
      "confirmationThresholdCents": {
        "type": "number",
        "default": 10000,
        "description": "Per-transaction amount (in cents) that requires human confirmation. Set to 0 to disable."
      },
      "anomalyMultiplier": {
        "type": "number",
        "default": 10,
        "description": "Multiplier over rolling average that triggers anomaly friction"
      },
      "anomalyMinSamples": {
        "type": "number",
        "default": 5,
        "description": "Minimum transaction count before anomaly detection activates"
      }
    }
  },
  "uiHints": {
    "enabled": {
      "label": "Enable Protection",
      "help": "Activate financial security checks on tool calls"
    },
    "maxVelocityCentsPerWindow": {
      "label": "Velocity Cap (cents)",
      "help": "Maximum cumulative spend in a sliding window before hard block"
    },
    "velocityWindowSeconds": {
      "label": "Velocity Window (seconds)"
    },
    "loopThreshold": {
      "label": "Loop Threshold",
      "help": "Identical calls within the window before hard block"
    },
    "loopWindowSeconds": {
      "label": "Loop Window (seconds)"
    },
    "confirmationThresholdCents": {
      "label": "Confirmation Threshold (cents)",
      "help": "Single-transaction amount requiring human approval. 0 = disabled."
    },
    "anomalyMultiplier": {
      "label": "Anomaly Multiplier",
      "help": "Flag transactions this many times above the rolling average"
    },
    "anomalyMinSamples": {
      "label": "Anomaly Min Samples",
      "help": "Transactions before anomaly detection kicks in"
    }
  }
}
